kibitzr_sentry.py
kibitzr_sentry-1.0.0.dist-info/METADATA
kibitzr_sentry-1.0.0.dist-info/RECORD
kibitzr_sentry-1.0.0.dist-info/WHEEL
kibitzr_sentry-1.0.0.dist-info/entry_points.txt
kibitzr_sentry-1.0.0.dist-info/top_level.txt
