Metadata-Version: 2.1
Name: kibitzr-sentry
Version: 1.0.0
Summary: Kibitzr integration with Sentry
Home-page: https://github.com/kibitzr/kibitzr-sentry
Author: Peter Demin
Author-email: kibitzrrr@gmail.com
License: MIT license
Keywords: kibitzr
Platform: UNKNOWN
Classifier: Development Status :: 5 - Production/Stable
Classifier: Intended Audience :: Developers
Classifier: License :: OSI Approved :: MIT License
Classifier: Natural Language :: English
Classifier: Programming Language :: Python :: 2
Classifier: Programming Language :: Python :: 2.6
Classifier: Programming Language :: Python :: 2.7
Classifier: Programming Language :: Python :: 3
Classifier: Programming Language :: Python :: 3.3
Classifier: Programming Language :: Python :: 3.4
Classifier: Programming Language :: Python :: 3.5
Classifier: Programming Language :: Python :: 3.6
Classifier: Programming Language :: Python :: 3.7
Requires-Dist: kibitzr
Requires-Dist: raven
